README.md
bootstrap.py
buildout.cfg
mr.sisyphus.cfg
setup.py
src/mr/__init__.py
src/mr.sisyphus.egg-info/PKG-INFO
src/mr.sisyphus.egg-info/SOURCES.txt
src/mr.sisyphus.egg-info/dependency_links.txt
src/mr.sisyphus.egg-info/entry_points.txt
src/mr.sisyphus.egg-info/namespace_packages.txt
src/mr.sisyphus.egg-info/not-zip-safe
src/mr.sisyphus.egg-info/requires.txt
src/mr.sisyphus.egg-info/top_level.txt
src/mr/sisyphus/__init__.py
src/mr/sisyphus/king.py