Metadata-Version: 1.0
Name: mr.sisyphus
Version: 1.0
Summary: His pointless toil will never end
Home-page: http://github.com/collective/mr.sisyphus
Author: Matthew Wilkes
Author-email: matthew@matthewwilkes.co.uk
License: BSD
Platform: UNKNOWN
Classifier: Programming Language :: Python
Classifier: Topic :: Software Development :: Libraries :: Python Modules
